wumpy/__init__.py
wumpy-0.0.0.dist-info/LICENSE
wumpy-0.0.0.dist-info/METADATA
wumpy-0.0.0.dist-info/WHEEL
wumpy-0.0.0.dist-info/top_level.txt
wumpy-0.0.0.dist-info/RECORD
