Metadata-Version: 2.1
Name: wumpy
Version: 0.0.0
Summary: Imagine an efficient and extensible Discord API wrapper
Home-page: UNKNOWN
Author: Bluenix
Author-email: bluenixdev@gmail.com
License: UNKNOWN
Platform: UNKNOWN
Classifier: Development Status :: 1 - Planning
Classifier: Intended Audience :: Developers
Classifier: License :: OSI Approved :: MIT License
Classifier: Natural Language :: English
Classifier: Operating System :: OS Independent
Classifier: Typing :: Typed
License-File: LICENSE
